{
   "shared" : {
      "NORINCO_12150L7" : {
         "fireStartingChance" : "0.12",
         "description" : "#china_vehicles:NORINCO_12150L7_descr",
         "tags" : "diesel",
         "maxRegenHealth" : 95,
         "maxHealth" : 190,
         "userString" : "#china_vehicles:NORINCO_12150L7",
         "repairCost" : 7,
         "level" : 8,
         "text" : "",
         "weight" : 750,
         "power" : 520,
         "price" : 79290,
         "notInShop" : null,
         "sound" : "/vehicles/tanks/heavy/IS_2"
      },
      "_12150L-3_V-12" : {
         "fireStartingChance" : "0.12",
         "description" : "#china_vehicles:_12150L-3_V-12_descr",
         "tags" : "diesel",
         "maxRegenHealth" : 52,
         "maxHealth" : 105,
         "userString" : "#china_vehicles:_12150L-3_V-12",
         "repairCost" : 4,
         "level" : 5,
         "text" : "",
         "weight" : 700,
         "power" : 430,
         "price" : 79290,
         "notInShop" : null,
         "sound" : "/vehicles/tanks/heavy/IS_2"
      },
      "text" : "",
      "_12150LZ" : {
         "fireStartingChance" : "0.12",
         "description" : "#china_vehicles:_12150LZ_descr",
         "tags" : "diesel",
         "maxRegenHealth" : 95,
         "maxHealth" : 190,
         "userString" : "#china_vehicles:_12150LZ",
         "repairCost" : 7,
         "level" : 8,
         "text" : "",
         "weight" : 750,
         "power" : 520,
         "price" : 79290,
         "notInShop" : null,
         "sound" : "/vehicles/tanks/heavy/IS_2"
      }
   },
   "ids" : {
      "NORINCO_12150L7" : "",
      "_12150L-3_V-12" : 1,
      "text" : "",
      "_12150LZ" : 2
   },
   "text" : ""
}
